heroserver/py.typed
heroserver/ai/ask.py
heroserver/ai/instruction.py
heroserver/ai/intent.py
heroserver/box/box.py
heroserver/box/box_api.py
heroserver/context/context.py
heroserver/dagu/client.py
heroserver/dagu/dag.py
heroserver/dagu/server.py
heroserver/doctools/html_replacer.py
heroserver/doctools/md_replacer.py
heroserver/doctools/processor.py
heroserver/hero/__init__.py
heroserver/hero/test_client.py
heroserver/heroscript/heroaction.py
heroserver/heroscript/heroscripts.py
heroserver/heroscript/mixin.py
heroserver/heroscript/tools.py
heroserver/herotools/__init__.py
heroserver/herotools/extensions.py
heroserver/herotools/gitscanner.py
heroserver/herotools/logger.py
heroserver/herotools/md5.py
heroserver/herotools/ourtime.py
heroserver/herotools/pathtools.py
heroserver/herotools/texttools.py
heroserver/infoserver/__init__.py
heroserver/infoserver/db.py
heroserver/infoserver/dbmem.py
heroserver/infoserver/dependencies.py
heroserver/infoserver/dependencies_old.py
heroserver/infoserver/ebook.py
heroserver/infoserver/slides.py
heroserver/infoserver/texttools.py
heroserver/jobclient/__init__.py
heroserver/jobclient/client.py
heroserver/jobmanager/__init__.py
heroserver/jobmanager/api.py
heroserver/jobmanager/db.py
heroserver/jobmanager/manager_actions.py
heroserver/jobmanager/manager_actors.py
heroserver/jobmanager/manager_agents.py
heroserver/jobmanager/manager_executors.py
heroserver/jobmanager/manager_jobs.py
heroserver/jobmanager/manager_logs.py
heroserver/jobmanager/manager_signing.py
heroserver/jobmanager/models.py
heroserver/jobmanager/run.py
heroserver/jobmanager/scheduler.py
heroserver/jobmanager/test_db.py
heroserver/jobmanager/test_jobqueue.py
heroserver/jobmanager/test_models.py
heroserver/mdcollections/__init__.py
heroserver/mdcollections/base_types.py
heroserver/mdcollections/factory.py
heroserver/mdcollections/mdcollections.py
heroserver/mdcollections/scanner.py
heroserver/mdcollections/tools.py
heroserver/mdserver/__init__.py
hero_server-0.1.2.dist-info/METADATA
hero_server-0.1.2.dist-info/WHEEL
hero_server-0.1.2.dist-info/top_level.txt
hero_server-0.1.2.dist-info/RECORD
